antlr4_cli/__init__.py
antlr4_cli/antlr4-4.13.2
antlr4_cli-4.13.2.dist-info/AUTHORS.md
antlr4_cli-4.13.2.dist-info/LICENSE
antlr4_cli-4.13.2.dist-info/METADATA
antlr4_cli-4.13.2.dist-info/WHEEL
antlr4_cli-4.13.2.dist-info/entry_points.txt
antlr4_cli-4.13.2.dist-info/top_level.txt
antlr4_cli-4.13.2.dist-info/RECORD
